gml/__init__.py
gml/compile.py
gml_ai-0.0.2.dist-info/METADATA
gml_ai-0.0.2.dist-info/WHEEL
gml_ai-0.0.2.dist-info/top_level.txt
gml_ai-0.0.2.dist-info/RECORD
